certbot_dns_f5xc/__init__.py
certbot_dns_f5xc/_internal/__init__.py
certbot_dns_f5xc/_internal/dns_f5xc.py
certbot_dns_f5xc-1.0.0.dist-info/licenses/LICENSE
certbot_dns_f5xc-1.0.0.dist-info/METADATA
certbot_dns_f5xc-1.0.0.dist-info/WHEEL
certbot_dns_f5xc-1.0.0.dist-info/entry_points.txt
certbot_dns_f5xc-1.0.0.dist-info/top_level.txt
certbot_dns_f5xc-1.0.0.dist-info/RECORD
