Metadata-Version: 2.4
Name: certbot-dns-f5xc
Version: 1.0.0
Summary: F5 Distributed Cloud (F5XC) DNS Authenticator plugin for Certbot
Home-page: https://github.com/fadlytabrani/certbot-dns-f5xc
Author: Fadly Tabrani
Author-email: Fadly Tabrani <fadly.tabrani@gmail.com>
Maintainer-email: Fadly Tabrani <fadly.tabrani@gmail.com>
License: Apache License 2.0
Project-URL: Homepage, https://github.com/fadlytabrani/certbot-dns-f5xc
Project-URL: Documentation, https://github.com/fadlytabrani/certbot-dns-f5xc#readme
Project-URL: Repository, https://github.com/fadlytabrani/certbot-dns-f5xc
Project-URL: Issues, https://github.com/fadlytabrani/certbot-dns-f5xc/issues
Project-URL: Changelog, https://github.com/fadlytabrani/certbot-dns-f5xc/releases
Keywords: certbot,dns,f5xc,lets-encrypt,ssl,certificate
Classifier: Development Status :: 4 - Beta
Classifier: Environment :: Plugins
Classifier: Intended Audience :: System Administrators
Classifier: License :: OSI Approved :: Apache Software License
Classifier: Operating System :: POSIX :: Linux
Classifier: Programming Language :: Python
Classifier: Programming Language :: Python :: 3
Classifier: Programming Language :: Python :: 3.8
Classifier: Programming Language :: Python :: 3.9
Classifier: Programming Language :: Python :: 3.10
Classifier: Programming Language :: Python :: 3.11
Classifier: Programming Language :: Python :: 3.12
Classifier: Topic :: Internet :: WWW/HTTP
Classifier: Topic :: Security
Classifier: Topic :: System :: Installation/Setup
Classifier: Topic :: System :: Networking
Classifier: Topic :: System :: Systems Administration
Classifier: Topic :: Utilities
Requires-Python: >=3.6
License-File: LICENSE
Requires-Dist: requests>=2.25.0
Requires-Dist: cryptography>=3.4.0
Requires-Dist: acme>=1.0.0
Requires-Dist: certbot>=1.0.0
Provides-Extra: dev
Requires-Dist: pytest>=6.0; extra == "dev"
Requires-Dist: pytest-cov>=2.0; extra == "dev"
Requires-Dist: black>=21.0; extra == "dev"
Requires-Dist: flake8>=3.8; extra == "dev"
Requires-Dist: mypy>=0.800; extra == "dev"
Dynamic: author
Dynamic: home-page
Dynamic: license-file
Dynamic: requires-python
